colocate/__init__.py
colocate/core.py
colocate/extension.py
colocate/pandas.py
colocate/polars.py
colocate/polars_og.py
colocate-0.1.2.dist-info/WHEEL
colocate-0.1.2.dist-info/METADATA
colocate-0.1.2.dist-info/RECORD
