Metadata-Version: 2.3
Name: colocate
Version: 0.1.2
Summary: DataFrame column reordering made simple
Keywords: dataframe,pandas,polars,columns,reorder,relocate,move,narwhals
Author: Albert Li
License: MIT
Requires-Dist: narwhals>=2.0.0
Requires-Dist: pandas>=2.0.0 ; extra == 'all'
Requires-Dist: polars>=1.0.0 ; extra == 'all'
Requires-Dist: pytest>=8.0.0 ; extra == 'dev'
Requires-Dist: pandas>=2.0.0 ; extra == 'dev'
Requires-Dist: polars>=1.0.0 ; extra == 'dev'
Requires-Dist: pandas>=2.0.0 ; extra == 'pandas'
Requires-Dist: polars>=1.0.0 ; extra == 'polars'
Requires-Python: >=3.12
Project-URL: Homepage, https://github.com/albertxli/colocate
Project-URL: Repository, https://github.com/albertxli/colocate
Provides-Extra: all
Provides-Extra: dev
Provides-Extra: pandas
Provides-Extra: polars
